forte.elastic-0.0.3-py3.7-nspkg.pth
fortex/elastic/__init__.py
fortex/elastic/elastic_indexer.py
fortex/elastic/elastic_search_index_processor.py
fortex/elastic/elastic_search_processor.py
fortex/elastic/elastic_search_query_creator.py
forte.elastic-0.0.3.dist-info/METADATA
forte.elastic-0.0.3.dist-info/WHEEL
forte.elastic-0.0.3.dist-info/namespace_packages.txt
forte.elastic-0.0.3.dist-info/top_level.txt
forte.elastic-0.0.3.dist-info/RECORD
