Metadata-Version: 2.1
Name: forte.elastic
Version: 0.0.3
Summary: Provide Forte implementations of a fantastic collection of NLP tools.
Home-page: https://github.com/asyml/forte-wrappers/tree/main/src/elastic
License: Apache License Version 2.0
Platform: any
Classifier: Intended Audience :: Developers
Classifier: Intended Audience :: Education
Classifier: Intended Audience :: Science/Research
Classifier: Operating System :: OS Independent
Classifier: Programming Language :: Python
Classifier: Programming Language :: Python :: 3.6
Classifier: Programming Language :: Python :: 3.7
Requires-Dist: forte (==0.2.0)
Requires-Dist: elasticsearch (<8.0.0,>=7.5.1) ; python_version < "3.9.0"
Requires-Dist: elasticsearch (<8.0.0,>=7.14.0) ; python_version >= "3.9.0"
